picfly/__init__.py
picfly/main.py
picfly/py.typed
picfly/tools/__init__.py
picfly/tools/ocr_client.py
picfly/tools/piclab.py
picfly/utils/__init__.py
picfly/utils/bm_ocr.py
picfly/utils/keyboard_name.py
picfly/utils/notify.py
picfly/utils/piclab_upload.py
picfly/utils/screenshot.py
picfly/utils/type_text.py
picfly-0.1.4.dist-info/licenses/LICENSE
picfly-0.1.4.dist-info/METADATA
picfly-0.1.4.dist-info/WHEEL
picfly-0.1.4.dist-info/entry_points.txt
picfly-0.1.4.dist-info/top_level.txt
picfly-0.1.4.dist-info/RECORD
