Metadata-Version: 2.4
Name: picfly
Version: 0.1.4
Summary: 图片工具：截图上传图床、OCR 文字识别，支持全局热键
Author-email: mofanx <yanwuning@live.cn>
Maintainer-email: mofanx <yanwuning@live.cn>
License: MIT
Project-URL: Homepage, https://github.com/mofanx/picfly
Project-URL: Repository, https://github.com/mofanx/picfly
Project-URL: Issues, https://github.com/mofanx/picfly/issues
Keywords: screenshot,ocr,image,upload,hotkey
Classifier: Development Status :: 4 - Beta
Classifier: Environment :: Win32 (MS Windows)
Classifier: Intended Audience :: Developers
Classifier: Intended Audience :: End Users/Desktop
Classifier: License :: OSI Approved :: MIT License
Classifier: Operating System :: Microsoft :: Windows
Classifier: Programming Language :: Python :: 3
Classifier: Programming Language :: Python :: 3.9
Classifier: Programming Language :: Python :: 3.10
Classifier: Programming Language :: Python :: 3.11
Classifier: Programming Language :: Python :: 3.12
Classifier: Topic :: Multimedia :: Graphics :: Capture :: Screen Capture
Classifier: Topic :: Utilities
Requires-Python: >=3.9
License-File: LICENSE
Requires-Dist: requests>=2.25.0
Requires-Dist: Pillow>=9.0.0
Requires-Dist: mss>=9.0.0
Requires-Dist: dbus-next>=0.2.3
Requires-Dist: keyboard>=0.13.5
Requires-Dist: pyclip>=0.7.0
Requires-Dist: tellit>=0.3.43
Provides-Extra: dev
Requires-Dist: pytest>=7.0.0; extra == "dev"
Requires-Dist: pytest-cov>=4.0.0; extra == "dev"
Requires-Dist: black>=23.0.0; extra == "dev"
Requires-Dist: ruff>=0.1.0; extra == "dev"
Provides-Extra: linux
Requires-Dist: dbus-python>=1.2.18; extra == "linux"
Dynamic: license-file
